{
  "baseUrl": "http://localhost:3000",
  "timestamp": "2026-06-07T16:50:17.329Z",
  "lighthouse": [
    {
      "page": "home",
      "url": "http://localhost:3000/",
      "performance": 58,
      "accessibility": 96,
      "bestPractices": 89,
      "seo": 100,
      "lcp": "3.1 s",
      "fcp": "2.4 s",
      "cls": "0",
      "tbt": "1,360 ms"
    },
    {
      "page": "past-events",
      "url": "http://localhost:3000/past-events",
      "performance": 0,
      "accessibility": 0,
      "bestPractices": 0,
      "seo": 0
    },
    {
      "page": "media-center",
      "url": "http://localhost:3000/media-center",
      "performance": 55,
      "accessibility": 97,
      "bestPractices": 93,
      "seo": 100,
      "lcp": "3.0 s",
      "fcp": "1.3 s",
      "cls": "0",
      "tbt": "3,090 ms"
    },
    {
      "page": "contact-us",
      "url": "http://localhost:3000/contact-us",
      "performance": 64,
      "accessibility": 96,
      "bestPractices": 93,
      "seo": 100,
      "lcp": "2.2 s",
      "fcp": "1.7 s",
      "cls": "0",
      "tbt": "1,340 ms"
    },
    {
      "page": "academic-council",
      "url": "http://localhost:3000/departments/academic-council",
      "performance": 51,
      "accessibility": 96,
      "bestPractices": 96,
      "seo": 100,
      "lcp": "4.4 s",
      "fcp": "1.8 s",
      "cls": "0",
      "tbt": "1,240 ms"
    },
    {
      "page": "committees",
      "url": "http://localhost:3000/committees",
      "performance": 66,
      "accessibility": 96,
      "bestPractices": 93,
      "seo": 100,
      "lcp": "2.0 s",
      "fcp": "1.6 s",
      "cls": "0",
      "tbt": "1,090 ms"
    }
  ],
  "seo": {
    "sitemap": {
      "status": 200,
      "ok": true,
      "urlCount": 104
    },
    "robots": {
      "status": 200,
      "ok": true,
      "hasSitemapDirective": true
    }
  },
  "links": {
    "error": "parse failed"
  },
  "redirects": {
    "totalRedirects": 37,
    "allPermanent": true,
    "issues": [],
    "pass": true
  },
  "goNoGo": {
    "performance": false,
    "accessibility": false,
    "seo": false,
    "cls": false,
    "links": false,
    "redirects": true,
    "recommendProduction": false
  }
}